{
	"authorize":{
		"permissions":[{
			"code":"*:/main/wode_yy.w:get",
			"id":"main_wode_yy.w",
			"name":"我的预约",
			"type":"menu",
			"ui":false
		}],
		"roles":[{
			"code":"authc",
			"id":"authc",
			"name":"注册用户",
			"permissions":["*:/main/wode_yy.w:get"]
		}]
	},
	"menu":{
		"children":[
			{
				"children":[],
				"ext":{},
				"order":0,
				"title":"我的预约",
				"types":["func"],
				"url":"/main/wode_yy.w"
			}
		],
		"ext":{},
		"order":0,
		"title":"鼎壹房产",
		"types":[]
	},
	"serviceInfo":{
		"label":"鼎壹房产",
		"name":"dingsheng"
	}
}